logicsponge/monitoring/__init__.py
logicsponge/monitoring/monitoring.py
logicsponge_monitoring-0.0.5.dist-info/METADATA
logicsponge_monitoring-0.0.5.dist-info/WHEEL
logicsponge_monitoring-0.0.5.dist-info/licenses/LICENSE
logicsponge_monitoring-0.0.5.dist-info/RECORD
