Metadata-Version: 2.4
Name: logicsponge-monitoring
Version: 0.0.5
Summary: A real-time data processing pipeline
Project-URL: Repository, https://github.com/innatelogic/logicsponge-monitoring.git
Author-email: Benedikt Bollig <bollig@lmf.cnrs.fr>, Matthias Függer <mfuegger@lmf.cnrs.fr>, Thomas Nowak <thomas@thomasnowak.net>
Maintainer-email: Benedikt Bollig <bollig@lmf.cnrs.fr>, Matthias Függer <mfuegger@lmf.cnrs.fr>, Thomas Nowak <thomas@thomasnowak.net>
License:                                  Apache License
License-File: LICENSE
Keywords: data processing,real-time,time series
Classifier: Development Status :: 4 - Beta
Classifier: Programming Language :: Python
Requires-Python: >=3.11
Requires-Dist: logicsponge
Requires-Dist: pytz
